{"domains":[{"email":"mao2116@mao.com","digit":"7","token":"token"},{"email":"be3948r6xf5r@popcornfarm7.com","token":"4TGSr1x8QZJaI-5ouU77","digit":"12"},{"email":"fahim@cloud-mail.top","token":"4KrDIl14Qybd5kxzdDee","digit":"5"},{"email":"dup98ym5408@plancetose.com","token":"azn5qFoPWFpz8fPpcDXo","digit":"11"},{"email":"wuhhgzv1y9ip@kjkszpjcompany.com","token":"HTdnwKb0js0eXckHpMHA","digit":"12"},{"email":"fsfsh@cloud-mail.top","token":"LJppSSWmrldp574kMfnk","digit":"5"},{"email":"bx707hllru4@crossmailjet.com","token":"jj1IQv-NrPnWSEcB2e-f","digit":"11"},{"email":"fahim@paperpapyrus.com","token":"2GviXemH0XQrWTMBOEVN","digit":"5"},{"email":"y4arypilfwslwyv@kjkszpjcompany.com","token":"Mb5Ab6XlPQfe3PeFYriq","digit":"15"},{"email":"fahjsd@cloud-mail.top","token":"rgDerVsZC4HAgm1eOIny","digit":"6"}]}